targeted_sum/TextReducer.py
targeted_sum/__init__.py
targeted_sum-1.0.9.dist-info/LICENSE
targeted_sum-1.0.9.dist-info/METADATA
targeted_sum-1.0.9.dist-info/WHEEL
targeted_sum-1.0.9.dist-info/top_level.txt
targeted_sum-1.0.9.dist-info/RECORD
